{
  "annotations": {
    "list": [
      {
        "builtIn": 1,
        "datasource": "-- Grafana --",
        "enable": true,
        "hide": true,
        "iconColor": "rgba(0, 211, 255, 1)",
        "name": "Annotations & Alerts",
        "type": "dashboard"
      }
    ]
  },
  "editable": true,
  "gnetId": null,
  "graphTooltip": 0,
  "id": 1,
  "iteration": 1585797467262,
  "links": [],
  "panels": [
    {
      "collapsed": false,
      "gridPos": {
        "h": 1,
        "w": 24,
        "x": 0,
        "y": 0
      },
      "id": 6,
      "panels": [],
      "title": "Collection",
      "type": "row"
    },
    {
      "cacheTimeout": null,
      "colorBackground": false,
      "colorValue": false,
      "colors": [
        "#d44a3a",
        "rgba(237, 129, 40, 0.89)",
        "#299c46"
      ],
      "datasource": null,
      "format": "percent",
      "gauge": {
        "maxValue": 100,
        "minValue": 0,
        "show": true,
        "thresholdLabels": false,
        "thresholdMarkers": true
      },
      "gridPos": {
        "h": 5,
        "w": 3,
        "x": 0,
        "y": 1
      },
      "id": 34,
      "interval": null,
      "links": [],
      "mappingType": 1,
      "mappingTypes": [
        {
          "name": "value to text",
          "value": 1
        },
        {
          "name": "range to text",
          "value": 2
        }
      ],
      "maxDataPoints": 100,
      "nullPointMode": "connected",
      "nullText": null,
      "postfix": "",
      "postfixFontSize": "50%",
      "prefix": "",
      "prefixFontSize": "50%",
      "rangeMaps": [
        {
          "from": "null",
          "text": "N/A",
          "to": "null"
        }
      ],
      "sparkline": {
        "fillColor": "rgba(31, 118, 189, 0.18)",
        "full": false,
        "lineColor": "rgb(31, 120, 193)",
        "show": false
      },
      "tableColumn": "",
      "targets": [
        {
          "expr": "(sum(shibuya_status_counter{run_id=\"$runID\", status=~\"2..\"}) by (run_id) / sum(shibuya_status_counter{run_id=\"$runID\"}) by (run_id))*100",
          "format": "time_series",
          "intervalFactor": 1,
          "refId": "A"
        }
      ],
      "thresholds": "90,98",
      "title": "2xx percentage",
      "type": "singlestat",
      "valueFontSize": "80%",
      "valueMaps": [
        {
          "op": "=",
          "text": "FAIL",
          "value": "null"
        }
      ],
      "valueName": "current"
    },
    {
      "aliasColors": {},
      "breakPoint": "50%",
      "cacheTimeout": null,
      "combine": {
        "label": "Others",
        "threshold": 0
      },
      "datasource": null,
      "decimals": null,
      "fontSize": "80%",
      "format": "none",
      "gridPos": {
        "h": 5,
        "w": 11,
        "x": 3,
        "y": 1
      },
      "id": 38,
      "interval": null,
      "legend": {
        "header": "",
        "percentage": true,
        "show": true,
        "values": true
      },
      "legendType": "Right side",
      "links": [],
      "maxDataPoints": 3,
      "nullPointMode": "connected",
      "pieType": "pie",
      "strokeWidth": 1,
      "targets": [
        {
          "expr": "sum(shibuya_status_counter{run_id=\"$runID\"}) by (status)",
          "format": "time_series",
          "intervalFactor": 1,
          "legendFormat": "{{status}}",
          "refId": "A"
        }
      ],
      "title": "Response Status",
      "transparent": true,
      "type": "grafana-piechart-panel",
      "valueName": "current"
    },
    {
      "aliasColors": {},
      "bars": false,
      "dashLength": 10,
      "dashes": false,
      "datasource": "shibuya_prom",
      "fill": 1,
      "gridPos": {
        "h": 5,
        "w": 10,
        "x": 14,
        "y": 1
      },
      "id": 2,
      "interval": "1s",
      "legend": {
        "alignAsTable": false,
        "avg": false,
        "current": true,
        "hideEmpty": false,
        "hideZero": false,
        "max": false,
        "min": false,
        "rightSide": false,
        "show": true,
        "total": false,
        "values": true
      },
      "lines": true,
      "linewidth": 1,
      "links": [],
      "nullPointMode": "connected",
      "percentage": false,
      "pointradius": 1,
      "points": false,
      "renderer": "flot",
      "seriesOverrides": [],
      "spaceLength": 10,
      "stack": false,
      "steppedLine": false,
      "targets": [
        {
          "expr": "(sum(rate(shibuya_latency_collection_sum{run_id=\"$runID\"}[2s])) by (run_id)) / (sum(rate(shibuya_status_counter{run_id=\"$runID\"}[2s])) by (run_id))",
          "format": "time_series",
          "hide": false,
          "instant": false,
          "interval": "",
          "intervalFactor": 1,
          "legendFormat": "Average",
          "refId": "A"
        },
        {
          "expr": "shibuya_latency_collection{run_id=\"$runID\"}",
          "format": "time_series",
          "hide": false,
          "intervalFactor": 1,
          "legendFormat": "{{quantile}}",
          "refId": "B"
        }
      ],
      "thresholds": [],
      "timeFrom": null,
      "timeShift": null,
      "title": "Overall latency for collection",
      "tooltip": {
        "shared": true,
        "sort": 0,
        "value_type": "individual"
      },
      "transparent": true,
      "type": "graph",
      "xaxis": {
        "buckets": null,
        "mode": "time",
        "name": null,
        "show": true,
        "values": []
      },
      "yaxes": [
        {
          "format": "ms",
          "label": null,
          "logBase": 1,
          "max": null,
          "min": null,
          "show": true
        },
        {
          "format": "ms",
          "label": null,
          "logBase": 1,
          "max": null,
          "min": null,
          "show": false
        }
      ],
      "yaxis": {
        "align": false,
        "alignLevel": 4
      }
    },
    {
      "cacheTimeout": null,
      "colorBackground": false,
      "colorValue": false,
      "colors": [
        "#299c46",
        "rgba(237, 129, 40, 0.89)",
        "#d44a3a"
      ],
      "datasource": null,
      "format": "none",
      "gauge": {
        "maxValue": 100,
        "minValue": 0,
        "show": false,
        "thresholdLabels": false,
        "thresholdMarkers": true
      },
      "gridPos": {
        "h": 2,
        "w": 3,
        "x": 0,
        "y": 6
      },
      "id": 23,
      "interval": "1s",
      "links": [],
      "mappingType": 1,
      "mappingTypes": [
        {
          "name": "value to text",
          "value": 1
        },
        {
          "name": "range to text",
          "value": 2
        }
      ],
      "maxDataPoints": 100,
      "nullPointMode": "connected",
      "nullText": null,
      "postfix": "",
      "postfixFontSize": "50%",
      "prefix": "",
      "prefixFontSize": "50%",
      "rangeMaps": [
        {
          "from": "null",
          "text": "N/A",
          "to": "null"
        }
      ],
      "sparkline": {
        "fillColor": "rgba(31, 118, 189, 0.18)",
        "full": false,
        "lineColor": "rgb(31, 120, 193)",
        "show": false
      },
      "tableColumn": "",
      "targets": [
        {
          "expr": "sum(shibuya_status_counter{run_id=\"$runID\"})",
          "format": "time_series",
          "interval": "1s",
          "intervalFactor": 1,
          "legendFormat": "",
          "refId": "A"
        }
      ],
      "thresholds": "",
      "title": "Total Requests",
      "type": "singlestat",
      "valueFontSize": "70%",
      "valueMaps": [
        {
          "op": "=",
          "text": "N/A",
          "value": "null"
        }
      ],
      "valueName": "current"
    },
    {
      "cacheTimeout": null,
      "colorBackground": false,
      "colorValue": false,
      "colors": [
        "#7eb26d",
        "#3f2b5b",
        "#dedaf7"
      ],
      "datasource": null,
      "format": "none",
      "gauge": {
        "maxValue": 100,
        "minValue": 0,
        "show": false,
        "thresholdLabels": false,
        "thresholdMarkers": true
      },
      "gridPos": {
        "h": 2,
        "w": 2,
        "x": 3,
        "y": 6
      },
      "id": 20,
      "interval": null,
      "links": [],
      "mappingType": 1,
      "mappingTypes": [
        {
          "name": "value to text",
          "value": 1
        },
        {
          "name": "range to text",
          "value": 2
        }
      ],
      "maxDataPoints": 100,
      "nullPointMode": "connected",
      "nullText": null,
      "postfix": "",
      "postfixFontSize": "100%",
      "prefix": "",
      "prefixFontSize": "100%",
      "rangeMaps": [
        {
          "from": "null",
          "text": "N/A",
          "to": "null"
        }
      ],
      "sparkline": {
        "fillColor": "rgba(31, 118, 189, 0.18)",
        "full": false,
        "lineColor": "rgb(31, 120, 193)",
        "show": false
      },
      "tableColumn": "",
      "targets": [
        {
          "expr": "count(shibuya_threads_gauge{run_id=\"$runID\"})",
          "format": "time_series",
          "instant": false,
          "intervalFactor": 1,
          "refId": "A"
        }
      ],
      "thresholds": "",
      "title": "Engines",
      "transparent": false,
      "type": "singlestat",
      "valueFontSize": "70%",
      "valueMaps": [
        {
          "op": "=",
          "text": "N/A",
          "value": "null"
        }
      ],
      "valueName": "current"
    },
    {
      "aliasColors": {},
      "bars": true,
      "dashLength": 10,
      "dashes": false,
      "datasource": "shibuya_prom",
      "fill": 1,
      "gridPos": {
        "h": 6,
        "w": 19,
        "x": 5,
        "y": 6
      },
      "id": 4,
      "interval": "1s",
      "legend": {
        "alignAsTable": true,
        "avg": false,
        "current": true,
        "hideEmpty": true,
        "hideZero": true,
        "max": true,
        "min": false,
        "rightSide": true,
        "show": true,
        "total": false,
        "values": true
      },
      "lines": true,
      "linewidth": 1,
      "links": [],
      "nullPointMode": "null",
      "percentage": false,
      "pointradius": 2,
      "points": false,
      "renderer": "flot",
      "seriesOverrides": [],
      "spaceLength": 10,
      "stack": false,
      "steppedLine": false,
      "targets": [
        {
          "expr": "sum(rate(shibuya_status_counter{run_id=\"$runID\"}[30s])) by (run_id)",
          "format": "time_series",
          "instant": false,
          "interval": "1s",
          "intervalFactor": 1,
          "legendFormat": "{{run_id}}",
          "refId": "A"
        },
        {
          "expr": "sum(rate(shibuya_status_counter{run_id=\"$runID\"}[30s])) by (plan_id)",
          "format": "time_series",
          "interval": "1s",
          "intervalFactor": 1,
          "legendFormat": "{{plan_id}}",
          "refId": "B"
        }
      ],
      "thresholds": [],
      "timeFrom": null,
      "timeShift": null,
      "title": "Overall QPS",
      "tooltip": {
        "shared": true,
        "sort": 0,
        "value_type": "individual"
      },
      "transparent": true,
      "type": "graph",
      "xaxis": {
        "buckets": null,
        "mode": "time",
        "name": null,
        "show": true,
        "values": []
      },
      "yaxes": [
        {
          "format": "short",
          "label": "QPS",
          "logBase": 1,
          "max": null,
          "min": null,
          "show": true
        },
        {
          "format": "short",
          "label": "",
          "logBase": 1,
          "max": null,
          "min": null,
          "show": false
        }
      ],
      "yaxis": {
        "align": false,
        "alignLevel": null
      }
    },
    {
      "aliasColors": {},
      "bars": false,
      "dashLength": 10,
      "dashes": false,
      "datasource": null,
      "decimals": 0,
      "fill": 0,
      "gridPos": {
        "h": 4,
        "w": 5,
        "x": 0,
        "y": 8
      },
      "id": 44,
      "legend": {
        "alignAsTable": false,
        "avg": false,
        "current": true,
        "max": true,
        "min": false,
        "rightSide": true,
        "show": true,
        "sideWidth": 90,
        "total": false,
        "values": true
      },
      "lines": true,
      "linewidth": 4,
      "links": [],
      "nullPointMode": "null",
      "percentage": false,
      "pointradius": 5,
      "points": false,
      "renderer": "flot",
      "seriesOverrides": [],
      "spaceLength": 10,
      "stack": false,
      "steppedLine": false,
      "targets": [
        {
          "expr": "sum(shibuya_threads_gauge{run_id=\"$runID\"})",
          "format": "time_series",
          "intervalFactor": 1,
          "legendFormat": " ",
          "refId": "A"
        }
      ],
      "thresholds": [],
      "timeFrom": null,
      "timeShift": null,
      "title": "Threads",
      "tooltip": {
        "shared": false,
        "sort": 0,
        "value_type": "individual"
      },
      "type": "graph",
      "xaxis": {
        "buckets": null,
        "mode": "time",
        "name": null,
        "show": false,
        "values": []
      },
      "yaxes": [
        {
          "format": "none",
          "label": null,
          "logBase": 1,
          "max": null,
          "min": null,
          "show": true
        },
        {
          "format": "short",
          "label": null,
          "logBase": 1,
          "max": null,
          "min": null,
          "show": false
        }
      ],
      "yaxis": {
        "align": false,
        "alignLevel": null
      }
    },
    {
      "columns": [],
      "datasource": null,
      "fontSize": "120%",
      "gridPos": {
        "h": 8,
        "w": 12,
        "x": 0,
        "y": 12
      },
      "hideTimeOverride": false,
      "id": 42,
      "links": [],
      "pageSize": null,
      "scroll": true,
      "showHeader": true,
      "sort": {
        "col": 6,
        "desc": false
      },
      "styles": [
        {
          "alias": "",
          "colorMode": null,
          "colors": [
            "rgba(245, 54, 54, 0.9)",
            "rgba(237, 129, 40, 0.89)",
            "rgba(50, 172, 45, 0.97)"
          ],
          "dateFormat": "YYYY-MM-DD HH:mm:ss",
          "decimals": 2,
          "mappingType": 1,
          "pattern": "Time",
          "thresholds": [],
          "type": "hidden",
          "unit": "short"
        },
        {
          "alias": "",
          "colorMode": null,
          "colors": [
            "rgba(245, 54, 54, 0.9)",
            "rgba(237, 129, 40, 0.89)",
            "rgba(50, 172, 45, 0.97)"
          ],
          "dateFormat": "YYYY-MM-DD HH:mm:ss",
          "decimals": 2,
          "mappingType": 1,
          "pattern": "__name__",
          "thresholds": [],
          "type": "hidden",
          "unit": "short"
        },
        {
          "alias": "",
          "colorMode": null,
          "colors": [
            "rgba(245, 54, 54, 0.9)",
            "rgba(237, 129, 40, 0.89)",
            "rgba(50, 172, 45, 0.97)"
          ],
          "dateFormat": "YYYY-MM-DD HH:mm:ss",
          "decimals": 2,
          "mappingType": 1,
          "pattern": "collection_id",
          "thresholds": [],
          "type": "hidden",
          "unit": "short"
        },
        {
          "alias": "",
          "colorMode": null,
          "colors": [
            "rgba(245, 54, 54, 0.9)",
            "rgba(237, 129, 40, 0.89)",
            "rgba(50, 172, 45, 0.97)"
          ],
          "dateFormat": "YYYY-MM-DD HH:mm:ss",
          "decimals": 2,
          "mappingType": 1,
          "pattern": "instance",
          "thresholds": [],
          "type": "hidden",
          "unit": "short"
        },
        {
          "alias": "",
          "colorMode": null,
          "colors": [
            "rgba(245, 54, 54, 0.9)",
            "rgba(237, 129, 40, 0.89)",
            "rgba(50, 172, 45, 0.97)"
          ],
          "dateFormat": "YYYY-MM-DD HH:mm:ss",
          "decimals": 2,
          "mappingType": 1,
          "pattern": "job",
          "thresholds": [],
          "type": "hidden",
          "unit": "short"
        },
        {
          "alias": "Count",
          "colorMode": null,
          "colors": [
            "rgba(245, 54, 54, 0.9)",
            "rgba(237, 129, 40, 0.89)",
            "rgba(50, 172, 45, 0.97)"
          ],
          "dateFormat": "YYYY-MM-DD HH:mm:ss",
          "decimals": 0,
          "mappingType": 1,
          "pattern": "Value",
          "thresholds": [],
          "type": "number",
          "unit": "none"
        },
        {
          "alias": "",
          "colorMode": null,
          "colors": [
            "rgba(245, 54, 54, 0.9)",
            "rgba(237, 129, 40, 0.89)",
            "rgba(50, 172, 45, 0.97)"
          ],
          "dateFormat": "YYYY-MM-DD HH:mm:ss",
          "decimals": 2,
          "mappingType": 1,
          "pattern": "run_id",
          "thresholds": [],
          "type": "hidden",
          "unit": "short"
        }
      ],
      "targets": [
        {
          "expr": "sum(shibuya_status_counter{run_id=\"$runID\"}) by (label, plan_id, status)",
          "format": "table",
          "hide": false,
          "instant": true,
          "interval": "",
          "intervalFactor": 1,
          "refId": "A"
        }
      ],
      "timeShift": null,
      "title": "Detailed response stats",
      "transform": "table",
      "transparent": true,
      "type": "table"
    },
    {
      "aliasColors": {},
      "bars": true,
      "dashLength": 10,
      "dashes": false,
      "datasource": "shibuya_prom",
      "fill": 1,
      "gridPos": {
        "h": 8,
        "w": 12,
        "x": 12,
        "y": 12
      },
      "id": 47,
      "interval": "1s",
      "legend": {
        "alignAsTable": false,
        "avg": false,
        "current": false,
        "hideEmpty": true,
        "hideZero": true,
        "max": false,
        "min": false,
        "rightSide": false,
        "show": true,
        "total": false,
        "values": false
      },
      "lines": false,
      "linewidth": 1,
      "links": [],
      "nullPointMode": "null",
      "percentage": false,
      "pointradius": 2,
      "points": false,
      "renderer": "flot",
      "seriesOverrides": [],
      "spaceLength": 10,
      "stack": true,
      "steppedLine": false,
      "targets": [
        {
          "expr": "sum(increase(shibuya_status_counter{run_id=\"$runID\", status!=\"200\"}[2s])) by (status)",
          "format": "time_series",
          "instant": false,
          "interval": "1s",
          "intervalFactor": 1,
          "legendFormat": "{{status}}",
          "refId": "A"
        }
      ],
      "thresholds": [],
      "timeFrom": null,
      "timeShift": null,
      "title": "Errors over time",
      "tooltip": {
        "shared": true,
        "sort": 2,
        "value_type": "individual"
      },
      "transparent": true,
      "type": "graph",
      "xaxis": {
        "buckets": null,
        "mode": "time",
        "name": null,
        "show": true,
        "values": []
      },
      "yaxes": [
        {
          "format": "short",
          "label": "Count",
          "logBase": 1,
          "max": null,
          "min": null,
          "show": true
        },
        {
          "format": "short",
          "label": "",
          "logBase": 1,
          "max": null,
          "min": null,
          "show": false
        }
      ],
      "yaxis": {
        "align": false,
        "alignLevel": null
      }
    },
    {
      "collapsed": true,
      "gridPos": {
        "h": 1,
        "w": 24,
        "x": 0,
        "y": 20
      },
      "id": 8,
      "panels": [
        {
          "cacheTimeout": null,
          "colorBackground": false,
          "colorValue": false,
          "colors": [
            "#d44a3a",
            "rgba(237, 129, 40, 0.89)",
            "#299c46"
          ],
          "datasource": null,
          "format": "percent",
          "gauge": {
            "maxValue": 100,
            "minValue": 0,
            "show": true,
            "thresholdLabels": false,
            "thresholdMarkers": true
          },
          "gridPos": {
            "h": 5,
            "w": 3,
            "x": 0,
            "y": 2
          },
          "id": 35,
          "interval": null,
          "links": [],
          "mappingType": 1,
          "mappingTypes": [
            {
              "name": "value to text",
              "value": 1
            },
            {
              "name": "range to text",
              "value": 2
            }
          ],
          "maxDataPoints": 100,
          "nullPointMode": "connected",
          "nullText": null,
          "postfix": "",
          "postfixFontSize": "50%",
          "prefix": "",
          "prefixFontSize": "50%",
          "rangeMaps": [
            {
              "from": "null",
              "text": "N/A",
              "to": "null"
            }
          ],
          "sparkline": {
            "fillColor": "rgba(31, 118, 189, 0.18)",
            "full": false,
            "lineColor": "rgb(31, 120, 193)",
            "show": false
          },
          "tableColumn": "",
          "targets": [
            {
              "expr": "(sum(shibuya_status_counter{run_id=\"$runID\", plan_id=\"$planID\", status=~\"2..\"}) by (plan_id) / sum(shibuya_status_counter{run_id=\"$runID\", plan_id=\"$planID\"}) by (plan_id))*100",
              "format": "time_series",
              "intervalFactor": 1,
              "refId": "A"
            }
          ],
          "thresholds": "90,98",
          "title": "2xx percentage",
          "type": "singlestat",
          "valueFontSize": "80%",
          "valueMaps": [
            {
              "op": "=",
              "text": "FAIL",
              "value": "null"
            }
          ],
          "valueName": "current"
        },
        {
          "aliasColors": {},
          "breakPoint": "50%",
          "cacheTimeout": null,
          "combine": {
            "label": "Others",
            "threshold": 0
          },
          "datasource": null,
          "decimals": null,
          "fontSize": "80%",
          "format": "none",
          "gridPos": {
            "h": 5,
            "w": 11,
            "x": 3,
            "y": 2
          },
          "id": 39,
          "interval": null,
          "legend": {
            "header": "",
            "percentage": true,
            "show": true,
            "values": true
          },
          "legendType": "Right side",
          "links": [],
          "maxDataPoints": 3,
          "nullPointMode": "connected",
          "pieType": "pie",
          "strokeWidth": 1,
          "targets": [
            {
              "expr": "sum(shibuya_status_counter{run_id=\"$runID\", plan_id=\"$planID\"}) by (status)",
              "format": "time_series",
              "intervalFactor": 1,
              "legendFormat": "{{status}}",
              "refId": "A"
            }
          ],
          "title": "Response Status",
          "transparent": true,
          "type": "grafana-piechart-panel",
          "valueName": "current"
        },
        {
          "aliasColors": {},
          "bars": false,
          "dashLength": 10,
          "dashes": false,
          "datasource": "shibuya_prom",
          "fill": 1,
          "gridPos": {
            "h": 5,
            "w": 10,
            "x": 14,
            "y": 2
          },
          "id": 31,
          "interval": "1s",
          "legend": {
            "avg": false,
            "current": true,
            "max": false,
            "min": false,
            "show": true,
            "total": false,
            "values": true
          },
          "lines": true,
          "linewidth": 1,
          "links": [],
          "nullPointMode": "connected",
          "percentage": false,
          "pointradius": 1,
          "points": false,
          "renderer": "flot",
          "seriesOverrides": [],
          "spaceLength": 10,
          "stack": false,
          "steppedLine": false,
          "targets": [
            {
              "expr": "(sum(rate(shibuya_latency_plan_sum{run_id=\"$runID\", plan_id=\"$planID\"}[2s])) by (plan_id)) / (sum(rate(shibuya_status_counter{run_id=\"$runID\", plan_id=\"$planID\"}[2s])) by (plan_id))",
              "format": "time_series",
              "instant": false,
              "interval": "",
              "intervalFactor": 1,
              "legendFormat": "Average",
              "refId": "A"
            },
            {
              "expr": "shibuya_latency_plan{plan_id=\"$planID\", run_id=\"$runID\"}",
              "format": "time_series",
              "intervalFactor": 1,
              "legendFormat": "{{quantile}}",
              "refId": "B"
            }
          ],
          "thresholds": [],
          "timeFrom": null,
          "timeShift": null,
          "title": "Latency percentile of plan",
          "tooltip": {
            "shared": true,
            "sort": 0,
            "value_type": "individual"
          },
          "transparent": true,
          "type": "graph",
          "xaxis": {
            "buckets": null,
            "mode": "time",
            "name": null,
            "show": true,
            "values": []
          },
          "yaxes": [
            {
              "format": "ms",
              "label": null,
              "logBase": 1,
              "max": null,
              "min": null,
              "show": true
            },
            {
              "format": "short",
              "label": null,
              "logBase": 1,
              "max": null,
              "min": null,
              "show": false
            }
          ],
          "yaxis": {
            "align": false,
            "alignLevel": null
          }
        },
        {
          "cacheTimeout": null,
          "colorBackground": false,
          "colorValue": false,
          "colors": [
            "#299c46",
            "rgba(237, 129, 40, 0.89)",
            "#d44a3a"
          ],
          "datasource": null,
          "format": "none",
          "gauge": {
            "maxValue": 100,
            "minValue": 0,
            "show": false,
            "thresholdLabels": false,
            "thresholdMarkers": true
          },
          "gridPos": {
            "h": 2,
            "w": 3,
            "x": 0,
            "y": 7
          },
          "id": 24,
          "interval": "1s",
          "links": [],
          "mappingType": 1,
          "mappingTypes": [
            {
              "name": "value to text",
              "value": 1
            },
            {
              "name": "range to text",
              "value": 2
            }
          ],
          "maxDataPoints": 100,
          "nullPointMode": "connected",
          "nullText": null,
          "postfix": "",
          "postfixFontSize": "50%",
          "prefix": "",
          "prefixFontSize": "50%",
          "rangeMaps": [
            {
              "from": "null",
              "text": "N/A",
              "to": "null"
            }
          ],
          "sparkline": {
            "fillColor": "rgba(31, 118, 189, 0.18)",
            "full": false,
            "lineColor": "rgb(31, 120, 193)",
            "show": false
          },
          "tableColumn": "",
          "targets": [
            {
              "expr": "sum(shibuya_status_counter{run_id=\"$runID\", plan_id=\"$planID\"})",
              "format": "time_series",
              "interval": "1s",
              "intervalFactor": 1,
              "legendFormat": "",
              "refId": "A"
            }
          ],
          "thresholds": "",
          "title": "Total Requests",
          "type": "singlestat",
          "valueFontSize": "70%",
          "valueMaps": [
            {
              "op": "=",
              "text": "N/A",
              "value": "null"
            }
          ],
          "valueName": "current"
        },
        {
          "cacheTimeout": null,
          "colorBackground": false,
          "colorValue": false,
          "colors": [
            "#7eb26d",
            "#3f2b5b",
            "#dedaf7"
          ],
          "datasource": null,
          "format": "none",
          "gauge": {
            "maxValue": 100,
            "minValue": 0,
            "show": false,
            "thresholdLabels": false,
            "thresholdMarkers": true
          },
          "gridPos": {
            "h": 2,
            "w": 2,
            "x": 3,
            "y": 7
          },
          "id": 45,
          "interval": null,
          "links": [],
          "mappingType": 1,
          "mappingTypes": [
            {
              "name": "value to text",
              "value": 1
            },
            {
              "name": "range to text",
              "value": 2
            }
          ],
          "maxDataPoints": 100,
          "nullPointMode": "connected",
          "nullText": null,
          "postfix": "",
          "postfixFontSize": "100%",
          "prefix": "",
          "prefixFontSize": "100%",
          "rangeMaps": [
            {
              "from": "null",
              "text": "N/A",
              "to": "null"
            }
          ],
          "sparkline": {
            "fillColor": "rgba(31, 118, 189, 0.18)",
            "full": false,
            "lineColor": "rgb(31, 120, 193)",
            "show": false
          },
          "tableColumn": "",
          "targets": [
            {
              "expr": "count(shibuya_threads_gauge{run_id=\"$runID\", plan_id=\"$planID\"})",
              "format": "time_series",
              "instant": false,
              "intervalFactor": 1,
              "refId": "A"
            }
          ],
          "thresholds": "",
          "title": "Engines",
          "transparent": false,
          "type": "singlestat",
          "valueFontSize": "70%",
          "valueMaps": [
            {
              "op": "=",
              "text": "N/A",
              "value": "null"
            }
          ],
          "valueName": "current"
        },
        {
          "aliasColors": {},
          "bars": true,
          "dashLength": 10,
          "dashes": false,
          "datasource": "shibuya_prom",
          "fill": 1,
          "gridPos": {
            "h": 6,
            "w": 19,
            "x": 5,
            "y": 7
          },
          "id": 17,
          "interval": "1s",
          "legend": {
            "alignAsTable": true,
            "avg": true,
            "current": true,
            "hideEmpty": true,
            "hideZero": true,
            "max": true,
            "min": false,
            "rightSide": true,
            "show": true,
            "total": false,
            "values": true
          },
          "lines": true,
          "linewidth": 1,
          "links": [],
          "nullPointMode": "null as zero",
          "percentage": false,
          "pointradius": 2,
          "points": false,
          "renderer": "flot",
          "seriesOverrides": [],
          "spaceLength": 10,
          "stack": false,
          "steppedLine": false,
          "targets": [
            {
              "expr": "sum(rate(shibuya_status_counter{run_id=\"$runID\", plan_id=\"$planID\"}[30s])) by (plan_id)",
              "format": "time_series",
              "instant": false,
              "interval": "1s",
              "intervalFactor": 1,
              "legendFormat": "{{plan_id}}",
              "refId": "A"
            },
            {
              "expr": "sum(rate(shibuya_status_counter{run_id=\"$runID\", plan_id=\"$planID\"}[30s])) by (label)",
              "format": "time_series",
              "interval": "1s",
              "intervalFactor": 1,
              "legendFormat": "{{label}}",
              "refId": "B"
            }
          ],
          "thresholds": [],
          "timeFrom": null,
          "timeShift": null,
          "title": "QPS",
          "tooltip": {
            "shared": false,
            "sort": 0,
            "value_type": "individual"
          },
          "transparent": true,
          "type": "graph",
          "xaxis": {
            "buckets": null,
            "mode": "time",
            "name": null,
            "show": true,
            "values": []
          },
          "yaxes": [
            {
              "format": "short",
              "label": "QPS",
              "logBase": 1,
              "max": null,
              "min": null,
              "show": true
            },
            {
              "format": "short",
              "label": "",
              "logBase": 1,
              "max": null,
              "min": null,
              "show": false
            }
          ],
          "yaxis": {
            "align": false,
            "alignLevel": null
          }
        },
        {
          "aliasColors": {},
          "bars": false,
          "dashLength": 10,
          "dashes": false,
          "datasource": null,
          "decimals": 0,
          "fill": 0,
          "gridPos": {
            "h": 4,
            "w": 5,
            "x": 0,
            "y": 9
          },
          "id": 46,
          "legend": {
            "alignAsTable": false,
            "avg": false,
            "current": true,
            "max": true,
            "min": false,
            "rightSide": true,
            "show": true,
            "sideWidth": 80,
            "total": false,
            "values": true
          },
          "lines": true,
          "linewidth": 4,
          "links": [],
          "nullPointMode": "null",
          "percentage": false,
          "pointradius": 5,
          "points": false,
          "renderer": "flot",
          "seriesOverrides": [],
          "spaceLength": 10,
          "stack": false,
          "steppedLine": false,
          "targets": [
            {
              "expr": "sum(shibuya_threads_gauge{run_id=\"$runID\", plan_id=\"$planID\"})",
              "format": "time_series",
              "intervalFactor": 1,
              "legendFormat": " ",
              "refId": "A"
            }
          ],
          "thresholds": [],
          "timeFrom": null,
          "timeShift": null,
          "title": "Threads",
          "tooltip": {
            "shared": false,
            "sort": 0,
            "value_type": "individual"
          },
          "type": "graph",
          "xaxis": {
            "buckets": null,
            "mode": "time",
            "name": null,
            "show": false,
            "values": []
          },
          "yaxes": [
            {
              "format": "short",
              "label": null,
              "logBase": 1,
              "max": null,
              "min": null,
              "show": true
            },
            {
              "format": "short",
              "label": null,
              "logBase": 1,
              "max": null,
              "min": null,
              "show": false
            }
          ],
          "yaxis": {
            "align": false,
            "alignLevel": null
          }
        },
        {
          "aliasColors": {},
          "bars": true,
          "dashLength": 10,
          "dashes": false,
          "datasource": "shibuya_prom",
          "fill": 1,
          "gridPos": {
            "h": 4,
            "w": 24,
            "x": 0,
            "y": 13
          },
          "id": 48,
          "interval": "1s",
          "legend": {
            "alignAsTable": false,
            "avg": false,
            "current": false,
            "hideEmpty": true,
            "hideZero": true,
            "max": false,
            "min": false,
            "rightSide": false,
            "show": true,
            "total": false,
            "values": false
          },
          "lines": false,
          "linewidth": 1,
          "links": [],
          "nullPointMode": "null",
          "percentage": false,
          "pointradius": 2,
          "points": false,
          "renderer": "flot",
          "seriesOverrides": [],
          "spaceLength": 10,
          "stack": true,
          "steppedLine": false,
          "targets": [
            {
              "expr": "sum(increase(shibuya_status_counter{run_id=\"$runID\", status!=\"200\", plan_id=\"$planID\"}[2s])) by (status)",
              "format": "time_series",
              "instant": false,
              "interval": "1s",
              "intervalFactor": 1,
              "legendFormat": "{{status}}",
              "refId": "A"
            }
          ],
          "thresholds": [],
          "timeFrom": null,
          "timeShift": null,
          "title": "Errors over time",
          "tooltip": {
            "shared": true,
            "sort": 2,
            "value_type": "individual"
          },
          "transparent": true,
          "type": "graph",
          "xaxis": {
            "buckets": null,
            "mode": "time",
            "name": null,
            "show": true,
            "values": []
          },
          "yaxes": [
            {
              "format": "short",
              "label": "Count",
              "logBase": 1,
              "max": null,
              "min": null,
              "show": true
            },
            {
              "format": "short",
              "label": "",
              "logBase": 1,
              "max": null,
              "min": null,
              "show": false
            }
          ],
          "yaxis": {
            "align": false,
            "alignLevel": null
          }
        }
      ],
      "title": "Plan",
      "type": "row"
    },
    {
      "collapsed": true,
      "gridPos": {
        "h": 1,
        "w": 24,
        "x": 0,
        "y": 21
      },
      "id": 12,
      "panels": [
        {
          "cacheTimeout": null,
          "colorBackground": false,
          "colorValue": false,
          "colors": [
            "#d44a3a",
            "rgba(237, 129, 40, 0.89)",
            "#299c46"
          ],
          "datasource": null,
          "format": "percent",
          "gauge": {
            "maxValue": 100,
            "minValue": 0,
            "show": true,
            "thresholdLabels": false,
            "thresholdMarkers": true
          },
          "gridPos": {
            "h": 5,
            "w": 3,
            "x": 0,
            "y": 3
          },
          "id": 36,
          "interval": null,
          "links": [],
          "mappingType": 1,
          "mappingTypes": [
            {
              "name": "value to text",
              "value": 1
            },
            {
              "name": "range to text",
              "value": 2
            }
          ],
          "maxDataPoints": 100,
          "nullPointMode": "connected",
          "nullText": null,
          "postfix": "",
          "postfixFontSize": "50%",
          "prefix": "",
          "prefixFontSize": "50%",
          "rangeMaps": [
            {
              "from": "null",
              "text": "N/A",
              "to": "null"
            }
          ],
          "sparkline": {
            "fillColor": "rgba(31, 118, 189, 0.18)",
            "full": false,
            "lineColor": "rgb(31, 120, 193)",
            "show": false
          },
          "tableColumn": "",
          "targets": [
            {
              "expr": "(sum(shibuya_status_counter{run_id=\"$runID\", label=\"$label\", status=~\"2..\"}) by (label) / sum(shibuya_status_counter{run_id=\"$runID\", label=\"$label\"}) by (label))*100",
              "format": "time_series",
              "intervalFactor": 1,
              "legendFormat": "",
              "refId": "A"
            }
          ],
          "thresholds": "90,98",
          "title": "2xx percentage",
          "type": "singlestat",
          "valueFontSize": "80%",
          "valueMaps": [
            {
              "op": "=",
              "text": "FAIL",
              "value": "null"
            }
          ],
          "valueName": "current"
        },
        {
          "aliasColors": {},
          "breakPoint": "50%",
          "cacheTimeout": null,
          "combine": {
            "label": "Others",
            "threshold": 0
          },
          "datasource": null,
          "decimals": null,
          "fontSize": "80%",
          "format": "none",
          "gridPos": {
            "h": 5,
            "w": 11,
            "x": 3,
            "y": 3
          },
          "id": 40,
          "interval": null,
          "legend": {
            "header": "",
            "percentage": true,
            "show": true,
            "values": true
          },
          "legendType": "Right side",
          "links": [],
          "maxDataPoints": 3,
          "nullPointMode": "connected",
          "pieType": "pie",
          "strokeWidth": 1,
          "targets": [
            {
              "expr": "sum(shibuya_status_counter{run_id=\"$runID\", label=\"$label\"}) by (status)",
              "format": "time_series",
              "intervalFactor": 1,
              "legendFormat": "{{status}}",
              "refId": "A"
            }
          ],
          "title": "Response Status",
          "transparent": true,
          "type": "grafana-piechart-panel",
          "valueName": "current"
        },
        {
          "aliasColors": {},
          "bars": false,
          "dashLength": 10,
          "dashes": false,
          "datasource": "shibuya_prom",
          "fill": 1,
          "gridPos": {
            "h": 5,
            "w": 10,
            "x": 14,
            "y": 3
          },
          "id": 32,
          "interval": "1s",
          "legend": {
            "avg": false,
            "current": true,
            "max": false,
            "min": false,
            "show": true,
            "total": false,
            "values": true
          },
          "lines": true,
          "linewidth": 1,
          "links": [],
          "nullPointMode": "connected",
          "percentage": false,
          "pointradius": 1,
          "points": false,
          "renderer": "flot",
          "seriesOverrides": [],
          "spaceLength": 10,
          "stack": false,
          "steppedLine": false,
          "targets": [
            {
              "expr": "(sum(rate(shibuya_latency_label_sum{run_id=\"$runID\", label=\"$label\"}[2s])) by (label)) / (sum(rate(shibuya_status_counter{run_id=\"$runID\", label=\"$label\"}[2s])) by (label))",
              "format": "time_series",
              "instant": false,
              "interval": "",
              "intervalFactor": 1,
              "legendFormat": "Average",
              "refId": "A"
            },
            {
              "expr": "shibuya_latency_label{label=\"$label\", run_id=\"$runID\"}",
              "format": "time_series",
              "intervalFactor": 1,
              "legendFormat": "{{quantile}}",
              "refId": "B"
            }
          ],
          "thresholds": [],
          "timeFrom": null,
          "timeShift": null,
          "title": "Latency Percentile of  label",
          "tooltip": {
            "shared": true,
            "sort": 0,
            "value_type": "individual"
          },
          "transparent": true,
          "type": "graph",
          "xaxis": {
            "buckets": null,
            "mode": "time",
            "name": null,
            "show": true,
            "values": []
          },
          "yaxes": [
            {
              "format": "ms",
              "label": null,
              "logBase": 1,
              "max": null,
              "min": null,
              "show": true
            },
            {
              "format": "short",
              "label": null,
              "logBase": 1,
              "max": null,
              "min": null,
              "show": false
            }
          ],
          "yaxis": {
            "align": false,
            "alignLevel": null
          }
        },
        {
          "cacheTimeout": null,
          "colorBackground": false,
          "colorValue": false,
          "colors": [
            "#299c46",
            "rgba(237, 129, 40, 0.89)",
            "#d44a3a"
          ],
          "datasource": null,
          "format": "none",
          "gauge": {
            "maxValue": 100,
            "minValue": 0,
            "show": false,
            "thresholdLabels": false,
            "thresholdMarkers": true
          },
          "gridPos": {
            "h": 3,
            "w": 3,
            "x": 0,
            "y": 8
          },
          "id": 25,
          "interval": "1s",
          "links": [],
          "mappingType": 1,
          "mappingTypes": [
            {
              "name": "value to text",
              "value": 1
            },
            {
              "name": "range to text",
              "value": 2
            }
          ],
          "maxDataPoints": 100,
          "nullPointMode": "connected",
          "nullText": null,
          "postfix": "",
          "postfixFontSize": "50%",
          "prefix": "",
          "prefixFontSize": "50%",
          "rangeMaps": [
            {
              "from": "null",
              "text": "N/A",
              "to": "null"
            }
          ],
          "sparkline": {
            "fillColor": "rgba(31, 118, 189, 0.18)",
            "full": false,
            "lineColor": "rgb(31, 120, 193)",
            "show": false
          },
          "tableColumn": "",
          "targets": [
            {
              "expr": "sum(shibuya_status_counter{run_id=\"$runID\", label=\"$label\"})",
              "format": "time_series",
              "interval": "1s",
              "intervalFactor": 1,
              "legendFormat": "",
              "refId": "A"
            }
          ],
          "thresholds": "",
          "title": "Total Requests",
          "type": "singlestat",
          "valueFontSize": "80%",
          "valueMaps": [
            {
              "op": "=",
              "text": "N/A",
              "value": "null"
            }
          ],
          "valueName": "current"
        },
        {
          "aliasColors": {},
          "bars": true,
          "dashLength": 10,
          "dashes": false,
          "datasource": "shibuya_prom",
          "fill": 1,
          "gridPos": {
            "h": 6,
            "w": 21,
            "x": 3,
            "y": 8
          },
          "id": 18,
          "interval": "1s",
          "legend": {
            "alignAsTable": true,
            "avg": true,
            "current": true,
            "hideEmpty": true,
            "hideZero": true,
            "max": true,
            "min": false,
            "rightSide": true,
            "show": true,
            "sortDesc": true,
            "total": false,
            "values": true
          },
          "lines": true,
          "linewidth": 1,
          "links": [],
          "nullPointMode": "null as zero",
          "percentage": false,
          "pointradius": 2,
          "points": false,
          "renderer": "flot",
          "seriesOverrides": [],
          "spaceLength": 10,
          "stack": false,
          "steppedLine": false,
          "targets": [
            {
              "expr": "sum(rate(shibuya_status_counter{run_id=\"$runID\", label=\"$label\"}[30s])) by (label)",
              "format": "time_series",
              "instant": false,
              "interval": "1s",
              "intervalFactor": 1,
              "legendFormat": "{{url}}",
              "refId": "A"
            }
          ],
          "thresholds": [],
          "timeFrom": null,
          "timeShift": null,
          "title": "QPS",
          "tooltip": {
            "shared": false,
            "sort": 0,
            "value_type": "individual"
          },
          "transparent": true,
          "type": "graph",
          "xaxis": {
            "buckets": null,
            "mode": "time",
            "name": null,
            "show": true,
            "values": []
          },
          "yaxes": [
            {
              "format": "short",
              "label": "QPS",
              "logBase": 1,
              "max": null,
              "min": null,
              "show": true
            },
            {
              "format": "short",
              "label": "",
              "logBase": 1,
              "max": null,
              "min": null,
              "show": false
            }
          ],
          "yaxis": {
            "align": false,
            "alignLevel": null
          }
        }
      ],
      "title": "Label",
      "type": "row"
    }
  ],
  "refresh": false,
  "schemaVersion": 16,
  "style": "dark",
  "tags": [],
  "templating": {
    "list": [
      {
        "allValue": null,
        "current": {
          "text": "1",
          "value": "1"
        },
        "datasource": "shibuya_prom",
        "hide": 2,
        "includeAll": false,
        "label": "Collection ID",
        "multi": false,
        "name": "collectionID",
        "options": [],
        "query": "label_values(collection_id)",
        "refresh": 2,
        "regex": "",
        "skipUrlSync": false,
        "sort": 3,
        "tagValuesQuery": "",
        "tags": [],
        "tagsQuery": "",
        "type": "query",
        "useTags": false
      },
      {
        "allValue": null,
        "current": {
          "text": "1",
          "value": "1"
        },
        "datasource": "shibuya_prom",
        "hide": 0,
        "includeAll": false,
        "label": "Plan ID",
        "multi": false,
        "name": "planID",
        "options": [],
        "query": "label_values(plan_id)",
        "refresh": 2,
        "regex": "",
        "skipUrlSync": false,
        "sort": 3,
        "tagValuesQuery": "",
        "tags": [],
        "tagsQuery": "",
        "type": "query",
        "useTags": false
      },
      {
        "allValue": null,
        "current": {
          "text": "harryHelp",
          "value": "harryHelp"
        },
        "datasource": "shibuya_prom",
        "hide": 0,
        "includeAll": false,
        "label": "Label",
        "multi": false,
        "name": "label",
        "options": [],
        "query": "label_values(label)",
        "refresh": 2,
        "regex": "",
        "skipUrlSync": false,
        "sort": 1,
        "tagValuesQuery": "",
        "tags": [],
        "tagsQuery": "",
        "type": "query",
        "useTags": false
      },
      {
        "allValue": null,
        "current": {
          "text": "5",
          "value": "5"
        },
        "datasource": "shibuya_prom",
        "hide": 2,
        "includeAll": false,
        "label": "Run ID",
        "multi": false,
        "name": "runID",
        "options": [],
        "query": "label_values(run_id)",
        "refresh": 2,
        "regex": "",
        "skipUrlSync": false,
        "sort": 4,
        "tagValuesQuery": "",
        "tags": [],
        "tagsQuery": "",
        "type": "query",
        "useTags": false
      }
    ]
  },
  "time": {
    "from": "2020-04-01T07:46:39.000Z",
    "to": "2020-04-01T07:51:45.000Z"
  },
  "timepicker": {
    "refresh_intervals": [
      "1s",
      "3s",
      "5s",
      "30s",
      "1m",
      "5m",
      "10m",
      "30m",
      "1h"
    ],
    "time_options": [
      "5m",
      "15m",
      "1h",
      "6h",
      "12h",
      "24h",
      "2d",
      "7d",
      "30d"
    ]
  },
  "timezone": "",
  "title": "shibuya",
  "uid": "RXY8nM1mk2",
  "version": 1
}